obsidianpilot/__init__.py
obsidianpilot/configure.py
obsidianpilot/constants.py
obsidianpilot/server.py
obsidianpilot/models/__init__.py
obsidianpilot/models/obsidian.py
obsidianpilot/tools/__init__.py
obsidianpilot/tools/fast_search.py
obsidianpilot/tools/image_management.py
obsidianpilot/tools/link_management.py
obsidianpilot/tools/note_management.py
obsidianpilot/tools/organization.py
obsidianpilot/tools/search_discovery.py
obsidianpilot/tools/view_note_images.py
obsidianpilot/utils/__init__.py
obsidianpilot/utils/filesystem.py
obsidianpilot/utils/fts_search.py
obsidianpilot/utils/index_updater.py
obsidianpilot/utils/persistent_index.py
obsidianpilot/utils/validation.py
obsidianpilot/utils/validators.py
obsidianpilot-2.1.3.dist-info/licenses/LICENSE
obsidianpilot-2.1.3.dist-info/METADATA
obsidianpilot-2.1.3.dist-info/WHEEL
obsidianpilot-2.1.3.dist-info/entry_points.txt
obsidianpilot-2.1.3.dist-info/top_level.txt
obsidianpilot-2.1.3.dist-info/RECORD
