Metadata-Version: 2.4
Name: ObsidianPilot
Version: 2.1.3
Summary: ObsidianPilot: Enhanced MCP server with token-efficient editing for Obsidian vaults
Author-email: that0n3guy <none@gmail.com>
License: MIT
Project-URL: Homepage, https://github.com/that0n3guy/ObsidianPilot
Project-URL: Repository, https://github.com/that0n3guy/ObsidianPilot
Project-URL: Issues, https://github.com/that0n3guy/ObsidianPilot/issues
Keywords: obsidian,mcp,fastmcp,llm,ai,notes,knowledge-management,token-efficient,pilot
Classifier: Development Status :: 4 - Beta
Classifier: Intended Audience :: Developers
Classifier: Programming Language :: Python :: 3
Classifier: Programming Language :: Python :: 3.10
Classifier: Programming Language :: Python :: 3.11
Classifier: Programming Language :: Python :: 3.12
Requires-Python: >=3.10
License-File: LICENSE
Requires-Dist: fastmcp>=2.8.1
Requires-Dist: httpx>=0.25.0
Requires-Dist: python-dotenv>=1.0.0
Requires-Dist: pydantic>=2.0.0
Requires-Dist: urllib3>=2.0.0
Requires-Dist: aiofiles>=23.0.0
Requires-Dist: pyyaml>=6.0.0
Requires-Dist: pillow>=9.0.0
Requires-Dist: aiosqlite>=0.19.0
Provides-Extra: dev
Requires-Dist: pytest>=7.0.0; extra == "dev"
Requires-Dist: pytest-asyncio>=0.21.0; extra == "dev"
Requires-Dist: pytest-mock>=3.10.0; extra == "dev"
Dynamic: license-file
